{
  "author": {
    "name": "Prashant Rawal",
    "company": "Tridhya Tech"
  },
  "title": "React with TypeScript",
  "subtitle": "for Tridhya Tech",
  "social": {
    "linkedin": "https://in.linkedin.com/in/prashant-rawal-12142b117",
    "github": "https://github.com/IAmCuriousDeveloper"
  },
  "description": "A workshop for start using TypeScript with React",
  "keywords": ["React", "react", "TypeScript", "workshop", "Prashant Rawal"],
  "productionBaseUrl": "/React-with-TypeScript",
  "csvPath": "./out/lessons.csv"
}
